pytorch_ml_utils/__init__.py
pytorch_ml_utils/get_lr_scheduler.py
pytorch_ml_utils/get_optimizer.py
pytorch_ml_utils/save_load.py
pytorch_ml_utils/utils.py
pytorch_ml_utils-0.1.0.dist-info/LICENSE
pytorch_ml_utils-0.1.0.dist-info/METADATA
pytorch_ml_utils-0.1.0.dist-info/WHEEL
pytorch_ml_utils-0.1.0.dist-info/top_level.txt
pytorch_ml_utils-0.1.0.dist-info/RECORD
