Metadata-Version: 2.1
Name: pytorch-ml-utils
Version: 0.1.0
Summary: Pytorch ML Utils
Home-page: https://github.com/trinhtuanvubk/pytorch-ml-utils
Author: Tuan-Vu Trinh
Author-email: tuanvutrinh.ai@gmail.com
License: MIT
Keywords: pytorch,accelerate,utils
Classifier: Development Status :: 4 - Beta
Classifier: Intended Audience :: Developers
Classifier: Topic :: Scientific/Engineering :: Artificial Intelligence
Classifier: License :: OSI Approved :: MIT License
Classifier: Programming Language :: Python :: 3.8
License-File: LICENSE
Requires-Dist: accelerate
Requires-Dist: optree
Requires-Dist: pytorch-warmup
Requires-Dist: torch >=2.0
